titiler/core/__init__.py
titiler/core/dependencies.py
titiler/core/errors.py
titiler/core/factory.py
titiler/core/middleware.py
titiler/core/py.typed
titiler/core/routing.py
titiler/core/telemetry.py
titiler/core/utils.py
titiler/core/algorithm/__init__.py
titiler/core/algorithm/base.py
titiler/core/algorithm/dem.py
titiler/core/algorithm/image.py
titiler/core/algorithm/index.py
titiler/core/algorithm/math.py
titiler/core/algorithm/ops.py
titiler/core/models/OGC.py
titiler/core/models/__init__.py
titiler/core/models/common.py
titiler/core/models/mapbox.py
titiler/core/models/responses.py
titiler/core/resources/__init__.py
titiler/core/resources/enums.py
titiler/core/resources/responses.py
titiler/core/templates/algorithm.html
titiler/core/templates/algorithms.html
titiler/core/templates/base.html
titiler/core/templates/colormap.html
titiler/core/templates/colormaps.html
titiler/core/templates/debug.html
titiler/core/templates/footer.html
titiler/core/templates/header.html
titiler/core/templates/map.html
titiler/core/templates/tilematrixset.html
titiler/core/templates/tilematrixsets.html
titiler/core/templates/tileset.html
titiler/core/templates/tilesets.html
titiler/core/templates/icons/clock.html
titiler/core/templates/icons/license.html
titiler/core/templates/icons/tag.html
titiler_core-1.0.2.dist-info/METADATA
titiler_core-1.0.2.dist-info/WHEEL
titiler_core-1.0.2.dist-info/licenses/LICENSE
titiler_core-1.0.2.dist-info/RECORD
